vtigerpy/__init__.py
vtigerpy/__version__.py
vtigerpy/core.py
vtigerpy-0.0.1.dist-info/LICENSE.txt
vtigerpy-0.0.1.dist-info/METADATA
vtigerpy-0.0.1.dist-info/WHEEL
vtigerpy-0.0.1.dist-info/top_level.txt
vtigerpy-0.0.1.dist-info/RECORD
