Metadata-Version: 2.1
Name: vtigerpy
Version: 0.0.1
Summary: A basic VTiger interface
Home-page: UNKNOWN
Author: Rodrigo Maluf
Author-email: rodrigo1793@gmail.com
Maintainer: Rodrigo Maluf
Maintainer-email: rodrigo1793@gmail.com
License: None
Keywords: python vtiger
Platform: UNKNOWN
Classifier: Intended Audience :: Developers
Classifier: Intended Audience :: System Administrators
Classifier: Operating System :: OS Independent
Classifier: Topic :: Internet :: WWW/HTTP
Classifier: Programming Language :: Python :: 2.6
Classifier: Programming Language :: Python :: 2.7
Classifier: Programming Language :: Python :: 3.3
Classifier: Programming Language :: Python :: 3.4
Classifier: Programming Language :: Python :: 3.5
Classifier: Programming Language :: Python :: 3.6
Classifier: Programming Language :: Python :: Implementation :: PyPy
